01_game_of_life/full_adder.sv
module full_adder (a, b, Cin, Cout, sum);

input wire a;
input wire b;
input wire Cin;
output logic Cout;
output logic sum;

logic p, q;

always_comb begin
    p = a ^ b;
    q = a & b;
    sum = Cin ^ p;
    Cout = (Cin & p) | q;
end
    
endmodule

01_game_of_life/three_bit_adder.sv
module three_bit_adder(a, b, Cout, sum);

input wire [2:0] a;
input wire [2:0] b;
output logic Cout;
output logic [2:0] sum;

wire carry0, carry1;
wire gnd = 0;
full_adder adder0(a[0],b[0],gnd,carry0,sum[0]);
full_adder adder1(a[1],b[1],carry0,carry1,sum[1]);
full_adder adder2(a[2],b[2],carry1,Cout,sum[2]);

endmodule

01_game_of_life/two_bit_adder.sv
module two_bit_adder(a, b, Cout, sum);

input wire [1:0] a;
input wire [1:0] b;
output logic Cout;
output logic [1:0] sum;

wire carry0;
full_adder adder0(a[0],b[0],0,carry0,sum[0]);
full_adder adder1(a[1],b[1],carry0,Cout,sum[1]);


endmodule

01_game_of_life/bit_counter.sv
module bit_counter (in, num);

input wire [7:0] in;
output logic [3:0] num;

wire gnd = 0;

// first layer counts pairs of wires
wire [1:0] count0, count1, count2, count3;
full_adder counter0(in[0],in[1],gnd,count0[1],count0[0]);
full_adder counter1(in[2],in[3],gnd,count1[1],count1[0]);
full_adder counter2(in[4],in[5],gnd,count2[1],count2[0]);
full_adder counter3(in[6],in[7],gnd,count3[1],count3[0]);

// second layer adds two bit counts
wire [2:0] sum0, sum1;
two_bit_adder adder0(count0,count1,sum0[2],sum0[1:0]);
two_bit_adder adder1(count2,count3,sum1[2],sum1[1:0]);

// third layer produces final count
three_bit_adder total(sum0,sum1,num[3],num[2:0]);

endmodule

01_game_of_life/test_bit_counter.sv
`timescale 1ns / 1ps
`default_nettype none

`define SIMULATION

module test_bit_counter;
    logic [7:0] in;
    logic [3:0] num;

    bit_counter UUT(in,num);

    initial begin
        $dumpfile("bit_counter.vcd");
        $dumpvars(0, UUT);

        in = 0;
        $display("in | num");
        for (int i = 0; i < 256; i = i + 1) begin
            in = i[7:0];
            #1 $display("%8b | %4b", in, num);
        end

        $finish;
    end
endmodule

01_game_of_life/bit_counter.vcd
$date
	Mon Oct  4 16:34:20 2021
$end
$version
	Icarus Verilog
$end
$timescale
	1ps
$end
$scope module test_bit_counter $end
$scope module UUT $end
$var wire 1 ! gnd $end
$var wire 8 " in [7:0] $end
$var wire 3 # sum1 [2:0] $end
$var wire 3 $ sum0 [2:0] $end
$var wire 4 % num [3:0] $end
$var wire 2 & count3 [1:0] $end
$var wire 2 ' count2 [1:0] $end
$var wire 2 ( count1 [1:0] $end
$var wire 2 ) count0 [1:0] $end
$scope module adder0 $end
$var wire 2 * a [1:0] $end
$var wire 2 + b [1:0] $end
$var wire 2 , sum [1:0] $end
$var wire 1 - carry0 $end
$var wire 1 . Cout $end
$scope module adder0 $end
$var wire 1 / Cin $end
$var wire 1 0 a $end
$var wire 1 1 b $end
$var reg 1 - Cout $end
$var reg 1 2 p $end
$var reg 1 3 q $end
$var reg 1 4 sum $end
$upscope $end
$scope module adder1 $end
$var wire 1 - Cin $end
$var wire 1 5 a $end
$var wire 1 6 b $end
$var reg 1 . Cout $end
$var reg 1 7 p $end
$var reg 1 8 q $end
$var reg 1 9 sum $end
$upscope $end
$upscope $end
$scope module adder1 $end
$var wire 2 : a [1:0] $end
$var wire 2 ; b [1:0] $end
$var wire 2 < sum [1:0] $end
$var wire 1 = carry0 $end
$var wire 1 > Cout $end
$scope module adder0 $end
$var wire 1 ? Cin $end
$var wire 1 @ a $end
$var wire 1 A b $end
$var reg 1 = Cout $end
$var reg 1 B p $end
$var reg 1 C q $end
$var reg 1 D sum $end
$upscope $end
$scope module adder1 $end
$var wire 1 = Cin $end
$var wire 1 E a $end
$var wire 1 F b $end
$var reg 1 > Cout $end
$var reg 1 G p $end
$var reg 1 H q $end
$var reg 1 I sum $end
$upscope $end
$upscope $end
$scope module counter0 $end
$var wire 1 ! Cin $end
$var wire 1 J a $end
$var wire 1 K b $end
$var reg 1 L Cout $end
$var reg 1 M p $end
$var reg 1 N q $end
$var reg 1 O sum $end
$upscope $end
$scope module counter1 $end
$var wire 1 ! Cin $end
$var wire 1 P a $end
$var wire 1 Q b $end
$var reg 1 R Cout $end
$var reg 1 S p $end
$var reg 1 T q $end
$var reg 1 U sum $end
$upscope $end
$scope module counter2 $end
$var wire 1 ! Cin $end
$var wire 1 V a $end
$var wire 1 W b $end
$var reg 1 X Cout $end
$var reg 1 Y p $end
$var reg 1 Z q $end
$var reg 1 [ sum $end
$upscope $end
$scope module counter3 $end
$var wire 1 ! Cin $end
$var wire 1 \ a $end
$var wire 1 ] b $end
$var reg 1 ^ Cout $end
$var reg 1 _ p $end
$var reg 1 ` q $end
$var reg 1 a sum $end
$upscope $end
$scope module total $end
$var wire 3 b a [2:0] $end
$var wire 3 c b [2:0] $end
$var wire 1 d gnd $end
$var wire 3 e sum [2:0] $end
$var wire 1 f carry1 $end
$var wire 1 g carry0 $end
$var wire 1 h Cout $end
$scope module adder0 $end
$var wire 1 d Cin $end
$var wire 1 i a $end
$var wire 1 j b $end
$var reg 1 g Cout $end
$var reg 1 k p $end
$var reg 1 l q $end
$var reg 1 m sum $end
$upscope $end
$scope module adder1 $end
$var wire 1 g Cin $end
$var wire 1 n a $end
$var wire 1 o b $end
$var reg 1 f Cout $end
$var reg 1 p p $end
$var reg 1 q q $end
$var reg 1 r sum $end
$upscope $end
$scope module adder2 $end
$var wire 1 f Cin $end
$var wire 1 s a $end
$var wire 1 t b $end
$var reg 1 h Cout $end
$var reg 1 u p $end
$var reg 1 v q $end
$var reg 1 w sum $end
$upscope $end
$upscope $end
$upscope $end
$upscope $end
$enddefinitions $end
#0
$dumpvars
0w
0v
0u
0t
0s
0r
0q
0p
0o
0n
0m
0l
0k
0j
0i
0h
0g
0f
b0 e
0d
b0 c
b0 b
0a
0`
0_
0^
0]
0\
0[
0Z
0Y
0X
0W
0V
0U
0T
0S
0R
0Q
0P
0O
0N
0M
0L
0K
0J
0I
0H
0G
0F
0E
0D
0C
0B
0A
0@
0?
0>
0=
b0 <
b0 ;
b0 :
09
08
07
06
05
04
03
02
01
00
0/
0.
0-
b0 ,
b0 +
b0 *
b0 )
b0 (
b0 '
b0 &
b0 %
b0 $
b0 #
b0 "
0!
$end
#1000
b1 %
b1 e
1m
1k
1i
b1 $
b1 b
b1 ,
14
12
10
b1 )
b1 *
1O
1M
1J
b1 "
#2000
0J
1K
b10 "
#3000
1r
1p
b10 %
b10 e
0m
0k
1n
0i
19
17
b10 $
b10 b
b10 ,
04
02
15
00
1L
b10 )
b10 *
0O
1N
0M
1J
b11 "
#4000
0r
0p
b1 %
b1 e
1m
1k
0n
1i
09
07
b1 $
b1 b
b1 ,
14
12
05
11
b0 )
b0 *
0L
0N
b1 (
b1 +
1U
1S
0J
0K
1P
b100 "
#5000
1r
1p
1n
b10 %
b10 e
0m
0k
19
0i
1-
b10 $
b10 b
b10 ,
04
13
02
10
b1 )
b1 *
1O
1M
1J
b101 "
#6000
0J
1K
b110 "
#7000
b11 %
b11 e
1m
1k
1i
17
0-
b11 $
b11 b
b11 ,
14
03
12
15
00
1L
b10 )
b10 *
0O
1N
0M
1J
b111 "
#8000
b1 %
b1 e
0r
0p
0n
b1 $
b1 b
b1 ,
09
07
05
b0 )
b0 *
0L
0N
0J
0K
0P
1Q
b1000 "
#9000
1r
1p
1n
b10 %
b10 e
0m
0k
19
0i
1-
b10 $
b10 b
b10 ,
04
13
02
10
b1 )
b1 *
1O
1M
1J
b1001 "
#10000
0J
1K
b1010 "
#11000
b11 %
b11 e
1m
1k
1i
17
0-
b11 $
b11 b
b11 ,
14
03
12
15
00
1L
b10 )
b10 *
0O
1N
0M
1J
b1011 "
#12000
b10 %
b10 e
0m
0k
0i
b10 $
b10 b
b10 ,
04
02
05
16
01
b0 )
b0 *
0L
0N
1R
b10 (
b10 +
0U
1T
0S
0J
0K
1P
b1100 "
#13000
b11 %
b11 e
1m
1k
1i
b11 $
b11 b
b11 ,
14
12
10
b1 )
b1 *
1O
1M
1J
b1101 "
#14000
0J
1K
b1110 "
#15000
1w
1u
0r
0p
b100 %
b100 e
0m
0k
1s
0n
0i
1.
09
18
07
b100 $
b100 b
b0 ,
04
02
15
00
1L
b10 )
b10 *
0O
1N
0M
1J
b1111 "
#16000
0w
0u
b1 %
b1 e
1m
1k
0s
1j
b0 $
b0 b
0.
08
b1 #
b1 c
b1 <
1D
1B
05
06
1@
b0 )
b0 *
0L
0N
b0 (
b0 +
0R
0T
b1 '
b1 :
1[
1Y
0J
0K
0P
0Q
1V
b10000 "
#17000
1r
1g
b10 %
b10 e
0m
1l
0k
1i
b1 $
b1 b
b1 ,
14
12
10
b1 )
b1 *
1O
1M
1J
b10001 "
#18000
0J
1K
b10010 "
#19000
1p
0g
b11 %
b11 e
1m
0l
1k
1n
0i
19
17
b10 $
b10 b
b10 ,
04
02
15
00
1L
b10 )
b10 *
0O
1N
0M
1J
b10011 "
#20000
0p
1g
b10 %
b10 e
0m
1l
0k
0n
1i
09
07
b1 $
b1 b
b1 ,
14
12
05
11
b0 )
b0 *
0L
0N
b1 (
b1 +
1U
1S
0J
0K
1P
b10100 "
#21000
1p
1n
0g
b11 %
b11 e
1m
0l
1k
19
0i
1-
b10 $
b10 b
b10 ,
04
13
02
10
b1 )
b1 *
1O
1M
1J
b10101 "
#22000
0J
1K
b10110 "
#23000
1w
1f
0r
1g
b100 %
b100 e
0m
1l
0k
1i
17
0-
b11 $
b11 b
b11 ,
14
03
12
15
00
1L
b10 )
b10 *
0O
1N
0M
1J
b10111 "
#24000
0w
0f
b10 %
b10 e
1r
0p
0n
b1 $
b1 b
b1 ,
09
07
05
b0 )
b0 *
0L
0N
0J
0K
0P
1Q
b11000 "
#25000
1p
1n
0g
b11 %
b11 e
1m
0l
1k
19
0i
1-
b10 $
b10 b
b10 ,
04
13
02
10
b1 )
b1 *
1O
1M
1J
b11001 "
#26000
0J
1K
b11010 "
#27000
1w
1f
0r
1g
b100 %
b100 e
0m
1l
0k
1i
17
0-
b11 $
b11 b
b11 ,
14
03
12
15
00
1L
b10 )
b10 *
0O
1N
0M
1J
b11011 "
#28000
0w
0f
1r
0g
b11 %
b11 e
1m
0l
1k
0i
b10 $
b10 b
b10 ,
04
02
05
16
01
b0 )
b0 *
0L
0N
1R
b10 (
b10 +
0U
1T
0S
0J
0K
1P
b11100 "
#29000
1w
1f
0r
1g
b100 %
b100 e
0m
1l
0k
1i
b11 $
b11 b
b11 ,
14
12
10
b1 )
b1 *
1O
1M
1J
b11101 "
#30000
0J
1K
b11110 "
#31000
1u
0f
0p
0g
b101 %
b101 e
1m
0l
1k
1s
0n
0i
1.
09
18
07
b100 $
b100 b
b0 ,
04
02
15
00
1L
b10 )
b10 *
0O
1N
0M
1J
b11111 "
#32000
b1 %
b1 e
0w
0u
0s
b0 $
b0 b
0.
08
05
06
b0 )
b0 *
0L
0N
b0 (
b0 +
0R
0T
0J
0K
0P
0Q
0V
1W
b100000 "
#33000
1r
1g
b10 %
b10 e
0m
1l
0k
1i
b1 $
b1 b
b1 ,
14
12
10
b1 )
b1 *
1O
1M
1J
b100001 "
#34000
0J
1K
b100010 "
#35000
1p
0g
b11 %
b11 e
1m
0l
1k
1n
0i
19
17
b10 $
b10 b
b10 ,
04
02
15
00
1L
b10 )
b10 *
0O
1N
0M
1J
b100011 "
#36000
0p
1g
b10 %
b10 e
0m
1l
0k
0n
1i
09
07
b1 $
b1 b
b1 ,
14
12
05
11
b0 )
b0 *
0L
0N
b1 (
b1 +
1U
1S
0J
0K
1P
b100100 "
#37000
1p
1n
0g
b11 %
b11 e
1m
0l
1k
19
0i
1-
b10 $
b10 b
b10 ,
04
13
02
10
b1 )
b1 *
1O
1M
1J
b100101 "
#38000
0J
1K
b100110 "
#39000
1w
1f
0r
1g
b100 %
b100 e
0m
1l
0k
1i
17
0-
b11 $
b11 b
b11 ,
14
03
12
15
00
1L
b10 )
b10 *
0O
1N
0M
1J
b100111 "
#40000
0w
0f
b10 %
b10 e
1r
0p
0n
b1 $
b1 b
b1 ,
09
07
05
b0 )
b0 *
0L
0N
0J
0K
0P
1Q
b101000 "
#41000
1p
1n
0g
b11 %
b11 e
1m
0l
1k
19
0i
1-
b10 $
b10 b
b10 ,
04
13
02
10
b1 )
b1 *
1O
1M
1J
b101001 "
#42000
0J
1K
b101010 "
#43000
1w
1f
0r
1g
b100 %
b100 e
0m
1l
0k
1i
17
0-
b11 $
b11 b
b11 ,
14
03
12
15
00
1L
b10 )
b10 *
0O
1N
0M
1J
b101011 "
#44000
0w
0f
1r
0g
b11 %
b11 e
1m
0l
1k
0i
b10 $
b10 b
b10 ,
04
02
05
16
01
b0 )
b0 *
0L
0N
1R
b10 (
b10 +
0U
1T
0S
0J
0K
1P
b101100 "
#45000
1w
1f
0r
1g
b100 %
b100 e
0m
1l
0k
1i
b11 $
b11 b
b11 ,
14
12
10
b1 )
b1 *
1O
1M
1J
b101101 "
#46000
0J
1K
b101110 "
#47000
1u
0f
0p
0g
b101 %
b101 e
1m
0l
1k
1s
0n
0i
1.
09
18
07
b100 $
b100 b
b0 ,
04
02
15
00
1L
b10 )
b10 *
0O
1N
0M
1J
b101111 "
#48000
0w
0u
1r
1p
b10 %
b10 e
0m
0k
0s
1o
0j
b0 $
b0 b
0.
08
1I
1G
b10 #
b10 c
b10 <
0D
0B
05
06
1E
0@
b0 )
b0 *
0L
0N
b0 (
b0 +
0R
0T
1X
b10 '
b10 :
0[
1Z
0Y
0J
0K
0P
0Q
1V
b110000 "
#49000
b11 %
b11 e
1m
1k
1i
b1 $
b1 b
b1 ,
14
12
10
b1 )
b1 *
1O
1M
1J
b110001 "
#50000
0J
1K
b110010 "
#51000
1w
1f
0r
1q
0p
b100 %
b100 e
0m
0k
1n
0i
19
17
b10 $
b10 b
b10 ,
04
02
15
00
1L
b10 )
b10 *
0O
1N
0M
1J
b110011 "
#52000
0w
0f
1r
0q
1p
b11 %
b11 e
1m
1k
0n
1i
09
07
b1 $
b1 b
b1 ,
14
12
05
11
b0 )
b0 *
0L
0N
b1 (
b1 +
1U
1S
0J
0K
1P
b110100 "
#53000
1w
1f
0r
1q
0p
1n
b100 %
b100 e
0m
0k
19
0i
1-
b10 $
b10 b
b10 ,
04
13
02
10
b1 )
b1 *
1O
1M
1J
b110101 "
#54000
0J
1K
b110110 "
#55000
b101 %
b101 e
1m
1k
1i
17
0-
b11 $
b11 b
b11 ,
14
03
12
15
00
1L
b10 )
b10 *
0O
1N
0M
1J
b110111 "
#56000
0w
0f
b11 %
b11 e
1r
0q
1p
0n
b1 $
b1 b
b1 ,
09
07
05
b0 )
b0 *
0L
0N
0J
0K
0P
1Q
b111000 "
#57000
1w
1f
0r
1q
0p
1n
b100 %
b100 e
0m
0k
19
0i
1-
b10 $
b10 b
b10 ,
04
13
02
10
b1 )
b1 *
1O
1M
1J
b111001 "
#58000
0J
1K
b111010 "
#59000
b101 %
b101 e
1m
1k
1i
17
0-
b11 $
b11 b
b11 ,
14
03
12
15
00
1L
b10 )
b10 *
0O
1N
0M
1J
b111011 "
#60000
b100 %
b100 e
0m
0k
0i
b10 $
b10 b
b10 ,
04
02
05
16
01
b0 )
b0 *
0L
0N
1R
b10 (
b10 +
0U
1T
0S
0J
0K
1P
b111100 "
#61000
b101 %
b101 e
1m
1k
1i
b11 $
b11 b
b11 ,
14
12
10
b1 )
b1 *
1O
1M
1J
b111101 "
#62000
0J
1K
b111110 "
#63000
1u
0f
1r
0q
1p
b110 %
b110 e
0m
0k
1s
0n
0i
1.
09
18
07
b100 $
b100 b
b0 ,
04
02
15
00
1L
b10 )
b10 *
0O
1N
0M
1J
b111111 "
#64000
0w
0u
0r
0p
b1 %
b1 e
1m
1k
0s
0o
1j
b0 $
b0 b
0.
08
0I
0G
b1 #
b1 c
b1 <
1D
1B
05
06
0E
1A
b0 )
b0 *
0L
0N
b0 (
b0 +
0R
0T
b0 '
b0 :
0X
0Z
b1 &
b1 ;
1a
1_
0J
0K
0P
0Q
0V
0W
1\
b1000000 "
#65000
1r
1g
b10 %
b10 e
0m
1l
0k
1i
b1 $
b1 b
b1 ,
14
12
10
b1 )
b1 *
1O
1M
1J
b1000001 "
#66000
0J
1K
b1000010 "
#67000
1p
0g
b11 %
b11 e
1m
0l
1k
1n
0i
19
17
b10 $
b10 b
b10 ,
04
02
15
00
1L
b10 )
b10 *
0O
1N
0M
1J
b1000011 "
#68000
0p
1g
b10 %
b10 e
0m
1l
0k
0n
1i
09
07
b1 $
b1 b
b1 ,
14
12
05
11
b0 )
b0 *
0L
0N
b1 (
b1 +
1U
1S
0J
0K
1P
b1000100 "
#69000
1p
1n
0g
b11 %
b11 e
1m
0l
1k
19
0i
1-
b10 $
b10 b
b10 ,
04
13
02
10
b1 )
b1 *
1O
1M
1J
b1000101 "
#70000
0J
1K
b1000110 "
#71000
1w
1f
0r
1g
b100 %
b100 e
0m
1l
0k
1i
17
0-
b11 $
b11 b
b11 ,
14
03
12
15
00
1L
b10 )
b10 *
0O
1N
0M
1J
b1000111 "
#72000
0w
0f
b10 %
b10 e
1r
0p
0n
b1 $
b1 b
b1 ,
09
07
05
b0 )
b0 *
0L
0N
0J
0K
0P
1Q
b1001000 "
#73000
1p
1n
0g
b11 %
b11 e
1m
0l
1k
19
0i
1-
b10 $
b10 b
b10 ,
04
13
02
10
b1 )
b1 *
1O
1M
1J
b1001001 "
#74000
0J
1K
b1001010 "
#75000
1w
1f
0r
1g
b100 %
b100 e
0m
1l
0k
1i
17
0-
b11 $
b11 b
b11 ,
14
03
12
15
00
1L
b10 )
b10 *
0O
1N
0M
1J
b1001011 "
#76000
0w
0f
1r
0g
b11 %
b11 e
1m
0l
1k
0i
b10 $
b10 b
b10 ,
04
02
05
16
01
b0 )
b0 *
0L
0N
1R
b10 (
b10 +
0U
1T
0S
0J
0K
1P
b1001100 "
#77000
1w
1f
0r
1g
b100 %
b100 e
0m
1l
0k
1i
b11 $
b11 b
b11 ,
14
12
10
b1 )
b1 *
1O
1M
1J
b1001101 "
#78000
0J
1K
b1001110 "
#79000
1u
0f
0p
0g
b101 %
b101 e
1m
0l
1k
1s
0n
0i
1.
09
18
07
b100 $
b100 b
b0 ,
04
02
15
00
1L
b10 )
b10 *
0O
1N
0M
1J
b1001111 "
#80000
1r
1p
0w
0u
1o
b10 %
b10 e
0m
0k
0s
1I
0j
b0 $
b0 b
0.
08
1=
b10 #
b10 c
b10 <
0D
1C
0B
05
06
1@
b0 )
b0 *
0L
0N
b0 (
b0 +
0R
0T
b1 '
b1 :
1[
1Y
0J
0K
0P
0Q
1V
b1010000 "
#81000
b11 %
b11 e
1m
1k
1i
b1 $
b1 b
b1 ,
14
12
10
b1 )
b1 *
1O
1M
1J
b1010001 "
#82000
0J
1K
b1010010 "
#83000
1w
1f
0r
1q
0p
b100 %
b100 e
0m
0k
1n
0i
19
17
b10 $
b10 b
b10 ,
04
02
15
00
1L
b10 )
b10 *
0O
1N
0M
1J
b1010011 "
#84000
0w
0f
1r
0q
1p
b11 %
b11 e
1m
1k
0n
1i
09
07
b1 $
b1 b
b1 ,
14
12
05
11
b0 )
b0 *
0L
0N
b1 (
b1 +
1U
1S
0J
0K
1P
b1010100 "
#85000
1w
1f
0r
1q
0p
1n
b100 %
b100 e
0m
0k
19
0i
1-
b10 $
b10 b
b10 ,
04
13
02
10
b1 )
b1 *
1O
1M
1J
b1010101 "
#86000
0J
1K
b1010110 "
#87000
b101 %
b101 e
1m
1k
1i
17
0-
b11 $
b11 b
b11 ,
14
03
12
15
00
1L
b10 )
b10 *
0O
1N
0M
1J
b1010111 "
#88000
0w
0f
b11 %
b11 e
1r
0q
1p
0n
b1 $
b1 b
b1 ,
09
07
05
b0 )
b0 *
0L
0N
0J
0K
0P
1Q
b1011000 "
#89000
1w
1f
0r
1q
0p
1n
b100 %
b100 e
0m
0k
19
0i
1-
b10 $
b10 b
b10 ,
04
13
02
10
b1 )
b1 *
1O
1M
1J
b1011001 "
#90000
0J
1K
b1011010 "
#91000
b101 %
b101 e
1m
1k
1i
17
0-
b11 $
b11 b
b11 ,
14
03
12
15
00
1L
b10 )
b10 *
0O
1N
0M
1J
b1011011 "
#92000
b100 %
b100 e
0m
0k
0i
b10 $
b10 b
b10 ,
04
02
05
16
01
b0 )
b0 *
0L
0N
1R
b10 (
b10 +
0U
1T
0S
0J
0K
1P
b1011100 "
#93000
b101 %
b101 e
1m
1k
1i
b11 $
b11 b
b11 ,
14
12
10
b1 )
b1 *
1O
1M
1J
b1011101 "
#94000
0J
1K
b1011110 "
#95000
1u
0f
1r
0q
1p
b110 %
b110 e
0m
0k
1s
0n
0i
1.
09
18
07
b100 $
b100 b
b0 ,
04
02
15
00
1L
b10 )
b10 *
0O
1N
0M
1J
b1011111 "
#96000
b10 %
b10 e
0w
0u
0s
b0 $
b0 b
0.
08
05
06
b0 )
b0 *
0L
0N
b0 (
b0 +
0R
0T
0J
0K
0P
0Q
0V
1W
b1100000 "
#97000
b11 %
b11 e
1m
1k
1i
b1 $
b1 b
b1 ,
14
12
10
b1 )
b1 *
1O
1M
1J
b1100001 "
#98000
0J
1K
b1100010 "
#99000
1w
1f
0r
1q
0p
b100 %
b100 e
0m
0k
1n
0i
19
17
b10 $
b10 b
b10 ,
04
02
15
00
1L
b10 )
b10 *
0O
1N
0M
1J
b1100011 "
#100000
0w
0f
1r
0q
1p
b11 %
b11 e
1m
1k
0n
1i
09
07
b1 $
b1 b
b1 ,
14
12
05
11
b0 )
b0 *
0L
0N
b1 (
b1 +
1U
1S
0J
0K
1P
b1100100 "
#101000
1w
1f
0r
1q
0p
1n
b100 %
b100 e
0m
0k
19
0i
1-
b10 $
b10 b
b10 ,
04
13
02
10
b1 )
b1 *
1O
1M
1J
b1100101 "
#102000
0J
1K
b1100110 "
#103000
b101 %
b101 e
1m
1k
1i
17
0-
b11 $
b11 b
b11 ,
14
03
12
15
00
1L
b10 )
b10 *
0O
1N
0M
1J
b1100111 "
#104000
0w
0f
b11 %
b11 e
1r
0q
1p
0n
b1 $
b1 b
b1 ,
09
07
05
b0 )
b0 *
0L
0N
0J
0K
0P
1Q
b1101000 "
#105000
1w
1f
0r
1q
0p
1n
b100 %
b100 e
0m
0k
19
0i
1-
b10 $
b10 b
b10 ,
04
13
02
10
b1 )
b1 *
1O
1M
1J
b1101001 "
#106000
0J
1K
b1101010 "
#107000
b101 %
b101 e
1m
1k
1i
17
0-
b11 $
b11 b
b11 ,
14
03
12
15
00
1L
b10 )
b10 *
0O
1N
0M
1J
b1101011 "
#108000
b100 %
b100 e
0m
0k
0i
b10 $
b10 b
b10 ,
04
02
05
16
01
b0 )
b0 *
0L
0N
1R
b10 (
b10 +
0U
1T
0S
0J
0K
1P
b1101100 "
#109000
b101 %
b101 e
1m
1k
1i
b11 $
b11 b
b11 ,
14
12
10
b1 )
b1 *
1O
1M
1J
b1101101 "
#110000
0J
1K
b1101110 "
#111000
1u
0f
1r
0q
1p
b110 %
b110 e
0m
0k
1s
0n
0i
1.
09
18
07
b100 $
b100 b
b0 ,
04
02
15
00
1L
b10 )
b10 *
0O
1N
0M
1J
b1101111 "
#112000
0w
0u
b11 %
b11 e
1m
1k
0s
1j
b0 $
b0 b
0.
08
1G
0=
b11 #
b11 c
b11 <
1D
0C
1B
05
06
1E
0@
b0 )
b0 *
0L
0N
b0 (
b0 +
0R
0T
1X
b10 '
b10 :
0[
1Z
0Y
0J
0K
0P
0Q
1V
b1110000 "
#113000
1w
1f
0r
1g
b100 %
b100 e
0m
1l
0k
1i
b1 $
b1 b
b1 ,
14
12
10
b1 )
b1 *
1O
1M
1J
b1110001 "
#114000
0J
1K
b1110010 "
#115000
1q
0p
0g
b101 %
b101 e
1m
0l
1k
1n
0i
19
17
b10 $
b10 b
b10 ,
04
02
15
00
1L
b10 )
b10 *
0O
1N
0M
1J
b1110011 "
#116000
0q
1p
1g
b100 %
b100 e
0m
1l
0k
0n
1i
09
07
b1 $
b1 b
b1 ,
14
12
05
11
b0 )
b0 *
0L
0N
b1 (
b1 +
1U
1S
0J
0K
1P
b1110100 "
#117000
1q
0p
1n
0g
b101 %
b101 e
1m
0l
1k
19
0i
1-
b10 $
b10 b
b10 ,
04
13
02
10
b1 )
b1 *
1O
1M
1J
b1110101 "
#118000
0J
1K
b1110110 "
#119000
1r
1g
b110 %
b110 e
0m
1l
0k
1i
17
0-
b11 $
b11 b
b11 ,
14
03
12
15
00
1L
b10 )
b10 *
0O
1N
0M
1J
b1110111 "
#120000
b100 %
b100 e
0r
0q
1p
0n
b1 $
b1 b
b1 ,
09
07
05
b0 )
b0 *
0L
0N
0J
0K
0P
1Q
b1111000 "
#121000
1q
0p
1n
0g
b101 %
b101 e
1m
0l
1k
19
0i
1-
b10 $
b10 b
b10 ,
04
13
02
10
b1 )
b1 *
1O
1M
1J
b1111001 "
#122000
0J
1K
b1111010 "
#123000
1r
1g
b110 %
b110 e
0m
1l
0k
1i
17
0-
b11 $
b11 b
b11 ,
14
03
12
15
00
1L
b10 )
b10 *
0O
1N
0M
1J
b1111011 "
#124000
0r
0g
b101 %
b101 e
1m
0l
1k
0i
b10 $
b10 b
b10 ,
04
02
05
16
01
b0 )
b0 *
0L
0N
1R
b10 (
b10 +
0U
1T
0S
0J
0K
1P
b1111100 "
#125000
1r
1g
b110 %
b110 e
0m
1l
0k
1i
b11 $
b11 b
b11 ,
14
12
10
b1 )
b1 *
1O
1M
1J
b1111101 "
#126000
0J
1K
b1111110 "
#127000
1u
0f
0q
1p
0g
b111 %
b111 e
1m
0l
1k
1s
0n
0i
1.
09
18
07
b100 $
b100 b
b0 ,
04
02
15
00
1L
b10 )
b10 *
0O
1N
0M
1J
b1111111 "
#128000
0w
0u
b1 %
b1 e
0r
0p
0s
0o
b0 $
b0 b
0.
08
b1 #
b1 c
b1 <
0I
0G
05
06
0E
b0 )
b0 *
0L
0N
b0 (
b0 +
0R
0T
b0 '
b0 :
0X
0Z
0J
0K
0P
0Q
0V
0W
0\
1]
b10000000 "
#129000
1r
1g
b10 %
b10 e
0m
1l
0k
1i
b1 $
b1 b
b1 ,
14
12
10
b1 )
b1 *
1O
1M
1J
b10000001 "
#130000
0J
1K
b10000010 "
#131000
1p
0g
b11 %
b11 e
1m
0l
1k
1n
0i
19
17
b10 $
b10 b
b10 ,
04
02
15
00
1L
b10 )
b10 *
0O
1N
0M
1J
b10000011 "
#132000
0p
1g
b10 %
b10 e
0m
1l
0k
0n
1i
09
07
b1 $
b1 b
b1 ,
14
12
05
11
b0 )
b0 *
0L
0N
b1 (
b1 +
1U
1S
0J
0K
1P
b10000100 "
#133000
1p
1n
0g
b11 %
b11 e
1m
0l
1k
19
0i
1-
b10 $
b10 b
b10 ,
04
13
02
10
b1 )
b1 *
1O
1M
1J
b10000101 "
#134000
0J
1K
b10000110 "
#135000
1w
1f
0r
1g
b100 %
b100 e
0m
1l
0k
1i
17
0-
b11 $
b11 b
b11 ,
14
03
12
15
00
1L
b10 )
b10 *
0O
1N
0M
1J
b10000111 "
#136000
0w
0f
b10 %
b10 e
1r
0p
0n
b1 $
b1 b
b1 ,
09
07
05
b0 )
b0 *
0L
0N
0J
0K
0P
1Q
b10001000 "
#137000
1p
1n
0g
b11 %
b11 e
1m
0l
1k
19
0i
1-
b10 $
b10 b
b10 ,
04
13
02
10
b1 )
b1 *
1O
1M
1J
b10001001 "
#138000
0J
1K
b10001010 "
#139000
1w
1f
0r
1g
b100 %
b100 e
0m
1l
0k
1i
17
0-
b11 $
b11 b
b11 ,
14
03
12
15
00
1L
b10 )
b10 *
0O
1N
0M
1J
b10001011 "
#140000
0w
0f
1r
0g
b11 %
b11 e
1m
0l
1k
0i
b10 $
b10 b
b10 ,
04
02
05
16
01
b0 )
b0 *
0L
0N
1R
b10 (
b10 +
0U
1T
0S
0J
0K
1P
b10001100 "
#141000
1w
1f
0r
1g
b100 %
b100 e
0m
1l
0k
1i
b11 $
b11 b
b11 ,
14
12
10
b1 )
b1 *
1O
1M
1J
b10001101 "
#142000
0J
1K
b10001110 "
#143000
1u
0f
0p
0g
b101 %
b101 e
1m
0l
1k
1s
0n
0i
1.
09
18
07
b100 $
b100 b
b0 ,
04
02
15
00
1L
b10 )
b10 *
0O
1N
0M
1J
b10001111 "
#144000
1r
1p
0w
0u
1o
b10 %
b10 e
0m
0k
0s
1I
0j
b0 $
b0 b
0.
08
1=
b10 #
b10 c
b10 <
0D
1C
0B
05
06
1@
b0 )
b0 *
0L
0N
b0 (
b0 +
0R
0T
b1 '
b1 :
1[
1Y
0J
0K
0P
0Q
1V
b10010000 "
#145000
b11 %
b11 e
1m
1k
1i
b1 $
b1 b
b1 ,
14
12
10
b1 )
b1 *
1O
1M
1J
b10010001 "
#146000
0J
1K
b10010010 "
#147000
1w
1f
0r
1q
0p
b100 %
b100 e
0m
0k
1n
0i
19
17
b10 $
b10 b
b10 ,
04
02
15
00
1L
b10 )
b10 *
0O
1N
0M
1J
b10010011 "
#148000
0w
0f
1r
0q
1p
b11 %
b11 e
1m
1k
0n
1i
09
07
b1 $
b1 b
b1 ,
14
12
05
11
b0 )
b0 *
0L
0N
b1 (
b1 +
1U
1S
0J
0K
1P
b10010100 "
#149000
1w
1f
0r
1q
0p
1n
b100 %
b100 e
0m
0k
19
0i
1-
b10 $
b10 b
b10 ,
04
13
02
10
b1 )
b1 *
1O
1M
1J
b10010101 "
#150000
0J
1K
b10010110 "
#151000
b101 %
b101 e
1m
1k
1i
17
0-
b11 $
b11 b
b11 ,
14
03
12
15
00
1L
b10 )
b10 *
0O
1N
0M
1J
b10010111 "
