01_game_of_life/full_adder.sv
module full_adder (a, b, Cin, Cout, sum);

input wire a;
input wire b;
input wire Cin;
output logic Cout;
output logic sum;

logic p, q;

always_comb begin
    p = a ^ b;
    q = a & b;
    sum = Cin ^ p;
    Cout = (Cin & p) | q;
end
    
endmodule

01_game_of_life/test_full_adder.sv
`timescale 1ns / 1ps
`default_nettype none

`define SIMULATION

module test_full_adder;
    logic [2:0] in;
    logic [1:0] out;

    full_adder UUT(in[0], in[1], in[2], out[1], out[0]);

    initial begin
        // collect waveforms
        $dumpfile("full_adder.vcd");
        $dumpvars(0, UUT);

        in = 0;
        $display("in | out");
        for (int i = 0; i < 8; i = i + 1) begin
            in = i[2:0];
            #1 $display("%2b | %2b", in, out);
        end

        $finish;
    end
    
endmodule

01_game_of_life/full_adder.vcd
$date
	Thu Sep 30 17:15:54 2021
$end
$version
	Icarus Verilog
$end
$timescale
	1ps
$end
$scope module test_full_adder $end
$scope module UUT $end
$var wire 1 ! Cin $end
$var wire 1 " a $end
$var wire 1 # b $end
$var reg 1 $ Cout $end
$var reg 1 % p $end
$var reg 1 & q $end
$var reg 1 ' sum $end
$upscope $end
$upscope $end
$enddefinitions $end
#0
$dumpvars
0'
0&
0%
0$
0#
0"
0!
$end
#1000
1'
1%
1"
#2000
0"
1#
#3000
1$
0'
1&
0%
1"
#4000
0$
1'
0&
0"
0#
1!
#5000
1$
0'
1%
1"
#6000
0"
1#
#7000
1'
1&
0%
1"
